MANIFEST.in
README.md
setup.py
pyzbx/__init__.py
pyzbx.egg-info/PKG-INFO
pyzbx.egg-info/SOURCES.txt
pyzbx.egg-info/dependency_links.txt
pyzbx.egg-info/pbr.json
pyzbx.egg-info/top_level.txt
pyzbx.egg-info/zip-safe