Metadata-Version: 1.1
Name: pyzbx
Version: 0.0.3
Summary: python get zabbix data api interface.
Home-page: https://github.com/davidbj/pyzbx
Author: shaozhi.zhang
Author-email: davidbjhd@gmail.com
License: MIT
Keywords: get zabbix data api.
Platform: UNKNOWN
Classifier: License :: OSI Approved :: MIT License
Classifier: Programming Language :: Python
Classifier: Intended Audience :: Developers
Classifier: Operating System :: OS Independent
